{
    "version":"1.0.0",
    "config":{
       "PEOPLE":{
          "outgoing":{
             "MARRIAGE":{
                "conditions":{
                   "PEOPLE_TO_MARRIAGE":{
                      "condition":{
                         "a":"id"
                      }
                   }
                }
             }
          }
       },
       "MARRIAGE":{
          "outgoing":{
             "PEOPLE":{
                "conditions":{
                   "MARRIAGE_a_TO_PEOPLE":{
                      "condition":{
                         "id":"a"
                      }
                   },
                   "MARRIAGE_b_TO_PEOPLE":{
                      "condition":{
                         "id":"b"
                      }
                   }
                }
             }
          }
       }
    }
 }